rds_utils/__init__.py
rds_utils/utils.py
rds_utils-0.1.0.dist-info/METADATA
rds_utils-0.1.0.dist-info/WHEEL
rds_utils-0.1.0.dist-info/top_level.txt
rds_utils-0.1.0.dist-info/RECORD
