Metadata-Version: 2.2
Name: rds-utils
Version: 0.1.0
Summary: A simple utility library providing helper functions for RDS
Project-URL: Homepage, https://github.com/soapergem/rds-utils
Project-URL: Repository, https://github.com/soapergem/rds-utils
Project-URL: Issues, https://github.com/soapergem/rds-utils/issues
Requires-Python: >=3.13
Requires-Dist: boto3>=1.36.12
